Workbook
Name Slicer_Product_Category: #N/A
Name Slicer_Region: #N/A
Name Slicer_Salesperson: #N/A

Sheet Raw_Data
A1: Order ID | B1: Order Date | C1: Region | D1: City | E1: Product Category | F1: Product | G1: Salesperson | H1: Units Sold | I1: Unit Price | J1: Discount | K1: Revenue | L1: Cost | M1: Profit | N1: Payment Method
A2: ORD-2025-0001 | B2: 45937 | C2: Central | D2: Lahore | E2: Electronics | F2: Headphones | G2: Sara Ahmed | H2: 4 | I2: 13857.85 | J2: 0.15 | K2: 47116.69 | L2: 32051.33 | M2: 15065.36 | N2: Digital Wallet
A3: ORD-2025-0002 | B3: 45990 | C3: North | D3: Islamabad | E3: Electronics | F3: Smartphone | G3: Bilal Hussain | H3: 4 | I3: 92078.83 | J3: 0 | K3: 368315.32 | L3: 274526.11 | M3: 93789.21 | N3: Credit Card
A4: ORD-2025-0003 | B4: 45768 | C4: South | D4: Quetta | E4: Home Appliances | F4: Air Conditioner | G4: Fatima Raza | H4: 3 | I4: 139279.81 | J4: 0.05 | K4: 396947.46 | L4: 299803.65 | M4: 97143.81 | N4: Cash
A5: ORD-2025-0004 | B5: 45932 | C5: North | D5: Rawalpindi | E5: Electronics | F5: Headphones | G5: Sara Ahmed | H5: 6 | I5: 14740.64 | J5: 0 | K5: 88443.84 | L5: 50237.2 | M5: 38206.64 | N5: Digital Wallet
A6: ORD-2025-0005 | B6: 45806 | C6: North | D6: Peshawar | E6: Home Appliances | F6: Vacuum Cleaner | G6: Sara Ahmed | H6: 4 | I6: 27883.75 | J6: 0 | K6: 111535 | L6: 73172.77 | M6: 38362.23 | N6: Credit Card
A7: ORD-2025-0006 | B7: 45794 | C7: North | D7: Rawalpindi | E7: Home Appliances | F7: Water Dispenser | G7: Sara Ahmed | H7: 6 | I7: 23177.6 | J7: 0.05 | K7: 132112.32 | L7: 93346.29 | M7: 38766.03 | N7: CREDIT CARD
A8: ORD-2025-0007 | B8: 45770 | C8: Central | D8: Multan | E8: Office Supplies | F8: Office Chair | G8: Fatima Raza | H8: 8 | I8: 27950.32 | J8: 0.15 | K8: 190062.18 | L8: 154762.04 | M8: 35300.14 | N8: Cash
A9: ORD-2025-0008 | B9: 45819 | C9: North | D9: Islamabad | E9: Home Appliances | F9: Water Dispenser | G9: Ayesha Noor | H9: 5 | I9: 22799.46 | J9: 0.1 | K9: 102597.57 | L9: 81476.31 | M9: 21121.26 | N9: Digital Wallet
A10: ORD-2025-0009 | B10: 45792 | C10: South | D10: Quetta | E10: Accessories | F10: USB Hub | G10: Bilal Hussain | H10: 5 | I10: 3957.83 | J10: 0.15 | K10: 16820.78 | L10: 10597.61 | M10: 6223.17 | N10: Digital Wallet
A11: ORD-2025-0010 | B11: 45739 | C11: South | D11: Karachi | E11: Office Supplies | F11: Keyboard | G11: Bilal Hussain | H11: 2 | I11: 8847.86 | J11: 0 | K11: 17695.72 | L11: 9610.85 | M11: 8084.87 | N11: Cash
A12: ORD-2025-0011 | B12: 02/10/2025 | C12: South | D12: Hyderabad | E12: Accessories | F12: Webcam | G12: Hamza Shah | H12: 1 | I12: 11831.72 | J12: 0 | K12: 11831.72 | L12: 6615.18 | M12: 5216.54 | N12: Bank Transfer
A13: ORD-2025-0012 | B13: 45792 | C13: North | D13: Rawalpindi | E13: Accessories | F13: USB Hub | G13: Usman Malik | H13: 8 | I13: 3866.18 | J13: 0.15 | K13: 26290.02 | L13: 17326 | M13: 8964.02 | N13: Cash
A14: ORD-2025-0013 | B14: 45929 | C14: Central | D14: Faisalabad | E14: Office Supplies | F14: Office Chair | G14: Ali Khan | H14: 6 | I14: 29697.05 | J14: 0.1 | K14: 160364.07 | L14: 118188.93 | M14: 42175.14 | N14: Bank Transfer
A15: ORD-2025-0014 | B15: 45698 | C15: South | D15: Karachi | E15: Electronics | F15: Headphones | G15: Sara Ahmed | H15: 5 | I15: 13895.53 | J15: 0 | K15: 69477.65 | L15: 42289.89 | M15: 27187.76 | N15: Digital Wallet
A16: ORD-2025-0015 | B16: 45968 | C16: North | D16: Peshawar | E16: Office Supplies | F16: Office Chair | G16: Bilal Hussain | H16: 8 | I16: 30537.63 | J16: 0 | K16: 244301.04 | L16: 150260.2 | M16: 94040.84 | N16: Credit Card
A17: ORD-2025-0016 | B17: 45922 | C17: central | D17: Multan | E17: Office Supplies | F17: Desk | G17: Zara Iqbal | H17: 7 | I17: 41010.51 | J17: 0.15 | K17: 244012.53 | L17: 181297.38 | M17: 62715.15 | N17: Cash
A18: ORD-2025-0017 | B18: 45661 | C18: North | D18: Islamabad | E18: Electronics | F18: Headphones | G18: Sara Ahmed | H18: 1 | I18: 14704.88 | J18: 0 | K18: 14704.88 | L18: 8291.76 | M18: 6413.12 | N18: Cash
A19: ORD-2025-0018 | B19: 45767 | C19: North | D19: Islamabad | E19: Electronics | F19: Headphones | G19: Usman Malik | H19: 2 | I19: 14532.84 | J19: 0.05 | K19: 27612.4 | L19: 16675.99 | M19: 10936.41 | N19: Digital Wallet
A20: ORD-2025-0019 | B20: 45868 | C20: North | D20: Rawalpindi | E20: Accessories | F20: USB Hub | G20: Zara Iqbal | H20: 2 | I20: 3929.14 | J20: 0.05 | K20: 7465.37 | L20: 4178.16 | M20: 3287.21 | N20: Cash
A21: ORD-2025-0020 | B21: 45755 | C21: Central | D21: Multan | E21: Electronics | F21: Laptop | G21: Zara Iqbal | H21: 7 | I21: 191755.12 | J21: 0 | K21: 1342285.8 | L21: 981481.51 | M21: 360804.33 | N21: Credit Card
A22: ORD-2025-0021 | B22: 45939 | C22: South | D22: Karachi | E22: Home Appliances | F22: Water Dispenser | G22: Sara Ahmed | H22: 4 | I22: 25967.98 | J22: 0 | K22: 103871.92 | L22: 63264.41 | M22: 40607.51 | N22: Cash
A23: ORD-2025-0022 | B23: 45863 | C23: Central | D23: Multan | E23: Electronics | F23: Laptop | G23: Ali Khan | H23: 4 | I23: 175122.81 | J23: 0.05 | K23: 665466.68 | L23: 570098.81 | M23: 95367.87 | N23: Credit Card
A24: ORD-2025-0023 | B24: 45942 | C24: South | D24: Karachi | E24: Accessories | F24: Webcam | G24: Zara Iqbal | H24: 8 | I24: 11104.86 | J24: 0.15 | K24: 75513.05 | L24: 53924.64 | M24: 21588.41 | N24: Credit Card
... A35: ORD-2025-0034 | B35: 45779 | C35: Central | D35: Lahore | E35: Electronics | F35: Headphones | G35: Usman Malik | H35: 7 | I35: 15599.3 | J35: 0.15 | K35: 92815.83 | L35: 56299 | M35: 36516.83 | N35: Credit Card
A36: ORD-2025-0035 | B36: 45794 | C36: South | D36: Karachi | E36: Office Supplies | F36: Desk | G36: Usman Malik | H36: 7 | I36: 39837.59 | J36: 0.15 | K36: 237033.66 | L36: 186868.95 | M36: 50164.71
A37: ORD-2025-0036 | B37: 45774 | C37: South | D37: Karachi | E37: Accessories | F37: USB Hub | G37: Ayesha Noor | H37: 4 | I37: 4412.75 | J37: 0.05 | K37: 16768.45 | L37: 8353.6 | M37: 8414.85 | N37: Cash
A38: ORD-2025-0037 | B38: 45918 | C38: Central | D38: Lahore | E38: Accessories | F38: Webcam | G38: Bilal Hussain | H38: 5 | I38: 12170.41 | J38: 0.05 | K38: 57809.45 | L38: 32323.86 | M38: 25485.59 | N38: Bank Transfer
A39: ORD-2025-0038 | B39: 45818 | C39: North | D39: Islamabad | E39: Home Appliances | F39: Microwave | G39: Bilal Hussain | H39: 5 | I39: 30562 | J39: 0.1 | K39: 137529 | L39: 112547.19 | M39: 24981.81 | N39: Cash
A40: ORD-2025-0039 | B40: 45933 | C40: South | D40: Quetta | E40: Office Supplies | F40: Desk | G40: Ayesha Noor | H40: 1 | I40: 39269.41 | J40: 0 | K40: 39269.41 | L40: 26166.26 | M40: 13103.15 | N40: Bank Transfer
A41: ORD-2025-0040 | B41: 45999 | C41: South | D41: Karachi | E41: Home Appliances | F41: Vacuum Cleaner | G41: Bilal Hussain | H41: 2 | I41: 27949.34 | J41: 0.05 | K41: 53103.75 | L41: 36197.95 | M41: 16905.8 | N41: Bank Transfer
A42: ORD-2025-0041 | B42: 45747 | C42: South | D42: Quetta | E42: Home Appliances | F42: Microwave | G42: Hamza Shah | H42: 4 | I42: 32579.96 | J42: 0.05 | K42: 123803.85 | L42: 91567.1 | M42: 32236.75 | N42: Digital Wallet
A43: ORD-2025-0042 | B43: 45822 | C43: Central | D43: Lahore | E43: Home Appliances | F43: Vacuum Cleaner | G43: Zara Iqbal | H43: 4 | I43: 26697.12 | J43: 0.1 | K43: 96109.63 | L43: 72897.57 | M43: 23212.06 | N43: Digital Wallet
A44: ORD-2025-0043 | B44: 45982 | C44: South | D44: Quetta | E44: Office Supplies | F44: Keyboard | G44: Fatima Raza | I44: 8716.04 | J44: 0.05 | K44: 24840.71 | L44: 14789.4 | M44: 10051.31 | N44: Cash
A45: ORD-2025-0044 | B45: 45901 | C45: North | D45: Peshawar | E45: Home Appliances | F45: Microwave | G45: Sara Ahmed | H45: 4 | I45: 31138.03 | J45: 0 | K45: 124552.12 | L45: 88842.51 | M45: 35709.61 | N45: Digital Wallet
A46: ORD-2025-0045 | B46: 45660 | C46: South | D46: Quetta | E46: Office Supplies | F46: Keyboard | G46: Sara Ahmed | H46: 8 | I46: 8363.53 | J46: 0 | K46: 66908.24 | L46: 39824.22 | M46: 27084.02 | N46: Digital Wallet
A47: ORD-2025-0046 | B47: 45895 | C47: North | D47: Islamabad | E47: Accessories | F47: Power Bank | G47: Fatima Raza | H47: 4 | I47: 6934.17 | J47: 0 | K47: 27736.68 | L47: 14428.11 | M47: 13308.57 | N47: Digital Wallet
A48: ORD-2025-0047 | B48: 45784 | C48: Central | D48: Multan | E48: Accessories | F48: Mouse | G48: Hamza Shah | H48: 3 | I48: 5402.72 | J48: 0.05 | K48: 15397.75 | L48: 8112.19 | M48: 7285.56 | N48: Digital Wallet
A49: ORD-2025-0048 | B49: 45821 | C49: Central | D49: Lahore | E49: Home Appliances | F49: Water Dispenser | G49: Sara Ahmed | H49: 2 | I49: 25337.1 | J49: 0 | K49: 50674.2 | L49: 31253.03 | M49: 19421.17 | N49: Credit Card
A50: ORD-2025-0049 | B50: 45896 | C50: North | D50: Islamabad | E50: Accessories | F50: USB Hub | G50: Bilal Hussain | H50: 4 | I50: 3907.16 | J50: 0.05 | K50: 14847.21 | L50: 8342.56 | M50: 6504.65 | N50: Cash
A51: ORD-2025-0050 | B51: 45857 | C51: North | D51: Rawalpindi | E51: Accessories | F51: Power Bank | G51: BILAL HUSSAIN | H51: 7 | I51: 6476.06 | J51: 0.05 | K51: 43065.8 | L51: 24970.75 | M51: 18095.05 | N51: Credit Card
A52: ORD-2025-0051 | B52: 45865 | C52: South | D52: Karachi | E52: Home Appliances | F52: Water Dispenser | G52: Usman Malik | H52: 8 | I52: 22653.78 | J52: 0.05 | K52: 172168.73 | L52: 128526.19 | M52: 43642.54 | N52: Digital Wallet
A53: ORD-2025-0052 | B53: 45894 | C53: North | D53: Peshawar | E53: Electronics | F53: Monitor | G53: Usman Malik | H53: 1 | I53: 48538.44 | J53: 0.05 | K53: 46111.52 | L53: 35751.71 | M53: 10359.81 | N53: Cash
A54: ORD-2025-0053 | B54: 45873 | C54: South | D54: Hyderabad | E54: Home Appliances | F54: Microwave | G54: Hamza Shah | H54: 8 | I54: 32085.75 | J54: 0.05 | K54: 243851.7 | L54: 178106.03 | M54: 65745.67 | N54: Cash
A55: ORD-2025-0054 | B55: 45673 | C55: South | D55: Karachi | E55: Electronics | F55: Headphones | G55: Ayesha Noor | H55: 4 | I55: 14848.33 | J55: 0.15 | K55: 50484.32 | L55: 31908.43 | M55: 18575.89 | N55: credit card
A56: ORD-2025-0055 | B56: 45769 | C56: North | D56: Peshawar | E56: Office Supplies | F56: Office Chair | G56: Zara Iqbal | H56: 3 | I56: 28379.44 | J56: 0 | K56: 85138.32 | L56: 57540.24 | M56: 27598.08 | N56: Bank Transfer
... A81: ORD-2025-0080 | B81: 46021 | C81: South | D81: Quetta | E81: Accessories | F81: Power Bank | G81: Usman Malik | H81: 1 | I81: 6992.07 | J81: 0.1 | K81: 6292.86 | L81: 3693.43 | M81: 2599.43 | N81: Bank Transfer
A82: ORD-2025-0081 | B82: 45718 | C82: Central | E82: Accessories | F82: Power Bank | G82: Usman Malik | H82: 4 | I82: 7011.95 | J82: 0 | K82: 28047.8 | L82: 14433.14 | M82: 13614.66 | N82: Digital Wallet
A83: ORD-2025-0082 | B83: 45732 | C83: Central | D83: Faisalabad | E83: Home Appliances | F83: Water Dispenser | G83: Bilal Hussain | H83: 8 | I83: 26382.56 | J83: 0 | K83: 211060.48 | L83: 126649.65 | M83: 84410.83 | N83: Credit Card
A84: ORD-2025-0083 | B84: 45917 | C84: Central | D84: Multan | E84: Office Supplies | F84: Printer | G84: Hamza Shah | H84: 5 | I84: 44876 | J84: 0.05 | K84: 213161 | L84: 154037.65 | M84: 59123.35 | N84: cash
A85: ORD-2025-0084 | B85: 45940 | C85: South | D85: Quetta | E85: Home Appliances | F85: Water Dispenser | G85: Bilal Hussain | H85: 3 | I85: 24290.47 | J85: 0.05 | K85: 69227.84 | L85: 47123.12 | M85: 22104.72 | N85: Digital Wallet
A86: ORD-2025-0085 | B86: 45900 | C86: South | D86: Karachi | E86: Office Supplies | F86: Keyboard | G86: Bilal Hussain | H86: 4 | I86: 8984.18 | J86: 0.05 | K86: 34139.88 | L86: 19071.88 | M86: 15068 | N86: Digital Wallet
A87: ORD-2025-0086 | B87: 45709 | C87: Central | E87: Office Supplies | F87: Keyboard | G87: Zara Iqbal | H87: 1 | I87: 7991.69 | J87: 0.1 | K87: 7192.52 | L87: 4866.87 | M87: 2325.65 | N87: Cash
A88: ORD-2025-0087 | B88: 45793 | C88: Central | D88: Faisalabad | E88: Electronics | F88: Smartphone | G88: Fatima Raza | H88: 7 | I88: 97460.13 | J88: 0 | K88: 682220.91 | L88: 464213.28 | M88: 218007.63 | N88: Bank transfer
A89: ORD-2025-0088 | B89: 45676 | C89: Central | D89: Lahore | E89: Home Appliances | F89: Water Dispenser | G89: Sara Ahmed | H89: 6 | I89: 24997.05 | J89: 0.05 | K89: 142483.18 | L89: 97745.13 | M89: 44738.05 | N89: Credit Card
A90: ORD-2025-0089 | B90: 46018 | C90: Central | D90: Multan | E90: Home Appliances | F90: Microwave | G90: Sara Ahmed | H90: 2 | I90: 32651.37 | J90: 0 | K90: 65302.74 | L90: 46045.16 | M90: 19257.58 | N90: Digital Wallet
A91: ORD-2025-0090 | B91: 45849 | C91: North | D91: Peshawar | E91: Home Appliances | F91: Air Conditioner | G91: Bilal Hussain | H91: 1 | I91: 131206.49 | J91: 0 | K91: 131206.49 | L91: 100044.11 | M91: 31162.38 | N91: Credit Card
A92: ORD-2025-0091 | B92: 45975 | C92: North | D92: Peshawar | E92: Accessories | F92: USB Hub | G92: Ayesha Noor | H92: 3 | I92: 3981.65 | J92: 0.1 | K92: 10750.46 | L92: 6495.04 | M92: 4255.42 | N92: digital wallet
A93: ORD-2025-0092 | B93: 45896 | C93: Central | D93: Lahore | E93: Office Supplies | F93: Keyboard | G93: Hamza Shah | H93: 5 | I93: 8445.02 | J93: 0.15 | K93: 35891.34 | L93: 23781.12 | M93: 12110.22 | N93: Credit Card
A94: ORD-2025-0093 | B94: 45759 | C94: North | D94: Rawalpindi | E94: Home Appliances | F94: Vacuum Cleaner | G94: Bilal Hussain | H94: 7 | I94: 27822.15 | J94: 0.05 | K94: 185017.3 | L94: 129675.58 | M94: 55341.72 | N94: Digital Wallet
A95: ORD-2025-0094 | B95: 45995 | C95: North | D95: Islamabad | E95: Accessories | F95: Webcam | G95: Bilal Hussain | H95: 5 | I95: 12406.55 | J95: 0.05 | K95: 58931.11 | L95: 31574.91 | M95: 27356.2 | N95: Bank Transfer
A96: ORD-2025-0095 | B96: 45838 | C96: North | D96: Peshawar | E96: Electronics | F96: Monitor | G96: Ayesha Noor | H96: 5 | I96: 54294.16 | J96: 0 | K96: 271470.8 | L96: 184780.26 | M96: 86690.54 | N96: Credit Card
A97: ORD-2025-0096 | B97: 45844 | C97: Central | D97: Faisalabad | E97: Office Supplies | F97: Printer | G97: Usman Malik | H97: 1 | I97: 41685.46 | J97: 0.05 | K97: 39601.19 | L97: 30142.4 | M97: 9458.79 | N97: Cash
A98: ORD-2025-0097 | B98: 07-Jul-2025 | C98: South | D98: Hyderabad | E98: Accessories | F98: USB Hub | G98: Hamza Shah | H98: 4 | I98: 3952.81 | J98: 0.1 | K98: 14230.12 | L98: 8663.36 | M98: 5566.76 | N98: Credit Card
A99: ORD-2025-0098 | B99: 45773 | C99: South | D99: Hyderabad | E99: Home Appliances | F99: Vacuum Cleaner | G99: Bilal Hussain | H99: 2 | I99: 26863.19 | J99: 0 | K99: 53726.38 | L99: 35274.71 | M99: 18451.67 | N99: Bank Transfer
A100: ORD-2025-0099 | B100: 45792 | C100: North | D100: Rawalpindi | E100: Electronics | F100: Headphones | G100: Bilal Hussain | H100: 2 | I100: 14395.1 | J100: 0.15 | K100: 24471.67 | L100: 16767.87 | M100: 7703.8 | N100: Bank Transfer
A101: ORD-2025-0100 | B101: 45970 | C101: North | D101: Peshawar | E101: Office Supplies | F101: Keyboard | G101: Ayesha Noor | H101: 1 | I101: 8662.58 | J101: 0.1 | K101: 7796.32 | L101: 4865.51 | M101: 2930.81 | N101: Cash
A102: ORD-2025-0101 | B102: 45910 | C102: Central | E102: Home Appliances | F102: Water Dispenser | G102: Sara Ahmed | H102: 2 | I102: 23087.93 | J102: 0 | K102: 46175.86 | L102: 31325.25 | M102: 14850.61 | N102: cash
A103: ORD-2025-0102 | B103: 45934 | C103: North | D103: Peshawar | E103: Office Supplies | F103: Keyboard | G103: Bilal Hussain | H103: 8 | I103: 8324.58 | J103: 0.15 | K103: 56607.14 | L103: 39935.15 | M103: 16671.99 | N103: Credit Card
A104: ORD-2025-0103 | B104: 45847 | C104: South | D104: Quetta | E104: Electronics | F104: Monitor | G104: Ayesha Noor | H104: 7 | I104: 55652.92 | J104: 0.05 | K104: 370091.92 | L104: 248420.13 | M104: 121671.79 | N104: Digital Wallet
A105: ORD-2025-0104 | B105: 45861 | C105: South | D105: Karachi | E105: HOME APPLIANCES | F105: Air Conditioner | G105: Hamza Shah | H105: 6 | I105: 135960.46 | J105: 0.15 | K105: 693398.35 | L105: 603034.94 | M105: 90363.41 | N105: Credit Card
A106: ORD-2025-0105 | B106: 45722 | C106: North | D106: Rawalpindi | E106: Electronics | F106: Smartphone | G106: Ayesha Noor | H106: 1 | I106: 85384.52 | J106: 0.05 | K106: 81115.29 | L106: 67119.39 | M106: 13995.9 | N106: Cash
A107: ORD-2025-0106 | B107: 45732 | C107: Central | D107: Lahore | E107: Office Supplies | F107: Office Chair | G107: Usman Malik | H107: 6 | I107: 29751.12 | J107: 0.1 | K107: 160656.05 | L107: 110602.63 | M107: 50053.42 | N107: Bank Transfer
A108: ORD-2025-0107 | B108: 45666 | C108: North | D108: Islamabad | E108: Electronics | F108: Smartphone | G108: Usman Malik | H108: 1 | I108: 89913.33 | J108: 0 | K108: 89913.33 | L108: 68762.94 | M108: 21150.39 | N108: Bank Transfer
A109: ORD-2025-0108 | B109: 45713 | C109: North | D109: Islamabad | E109: Accessories | F109: Power Bank | G109: Zara Iqbal | H109: 2 | I109: 6475.3 | J109: 0.05 | K109: 12303.07 | L109: 7242.67 | M109: 5060.4 | N109: Credit Card
A110: ORD-2025-0109 | B110: 45876 | C110: Central | E110: home appliances | F110: Water Dispenser | G110: Sara Ahmed | H110: 1 | I110: 22778.44 | J110: 0.05 | K110: 21639.52 | L110: 16263.11 | M110: 5376.41 | N110: Digital Wallet
A111: ORD-2025-0110 | B111: 45977 | C111: Central | D111: Faisalabad | E111: Electronics | F111: Laptop | G111: Fatima Raza | H111: 6 | I111: 188205.6 | J111: 0 | K111: 1129233.6 | L111: 833966.07 | M111: 295267.53 | N111: Digital Wallet
A112: ORD-2025-0111 | B112: 45993 | C112: Central | D112: Multan | E112: home appliances | F112: Water Dispenser | G112: Ayesha Noor | H112: 7 | I112: 22928.78 | J112: 0.15 | K112: 136426.24 | L112: 108167.79 | M112: 28258.45 | N112: Digital Wallet
A113: ORD-2025-0112 | B113: 45876 | C113: South | D113: Karachi | E113: Accessories | F113: Webcam | G113: Fatima Raza | H113: 8 | I113: 11313.66 | J113: 0.15 | K113: 76932.89 | L113: 50786.11 | M113: 26146.78 | N113: Bank Transfer
A114: ORD-2025-0113 | B114: 45848 | C114: South | D114: Karachi | E114: Accessories | F114: Power Bank | G114: Usman Malik | H114: 2 | I114: 6845.04 | J114: 0 | K114: 13690.08 | L114: 7201.67 | M114: 6488.41 | N114: Cash
A115: ORD-2025-0114 | B115: 45874 | C115: Central | D115: Multan | E115: Home Appliances | F115: Air Conditioner | G115: Ali Khan | H115: 7 | I115: 131837.72 | J115: 0.15 | K115: 784434.43 | L115: 732366.52 | M115: 52067.91 | N115: Bank Transfer
A116: ORD-2025-0115 | B116: 45713 | C116: Central | D116: Faisalabad | E116: Home Appliances | F116: Air Conditioner | G116: Fatima Raza | H116: 4 | I116: 127542.17 | J116: 0.05 | K116: 484660.25 | L116: 398221.64 | M116: 86438.61 | N116: Bank Transfer
A117: ORD-2025-0116 | B117: 45794 | C117: North | D117: Rawalpindi | E117: Office Supplies | F117: Keyboard | G117: Ali Khan | H117: 1 | I117: 8648.23 | J117: 0.15 | K117: 7351 | L117: 5037.51 | M117: 2313.49 | N117: Credit Card
A118: ORD-2025-0117 | B118: 45863 | C118: South | D118: Quetta | E118: Home Appliances | F118: Vacuum Cleaner | G118: Sara Ahmed | H118: 6 | I118: 24866.38 | J118: 0 | K118: 149198.28 | L118: 109041.39 | M118: 40156.89 | N118: Credit Card
A119: ORD-2025-0118 | B119: 45847 | C119: Central | D119: Multan | E119: Electronics | F119: Laptop | G119: Hamza Shah | H119: 4 | I119: 181335.35 | J119: 0.05 | K119: 689074.33 | L119: 564514.02 | M119: 124560.31 | N119: Bank Transfer
A120: ORD-2025-0119 | B120: 45699 | C120: Central | D120: Multan | E120: Electronics | F120: Laptop | G120: Hamza Shah | H120: 3 | I120: 174859.33 | J120: 0.1 | K120: 472120.19 | L120: 414703.92 | M120: 57416.27 | N120: Digital Wallet
A121: ORD-2025-0120 | B121: 45878 | C121: Central | D121: Faisalabad | E121: Accessories | F121: Mouse | G121: Sara Ahmed | H121: 7 | I121: 5011.27 | J121: 0.1 | K121: 31571 | L121: 18483.58 | M121: 13087.42 | N121: Bank Transfer
A122: ORD-2025-0121 | B122: 45762 | C122: Central | D122: Multan | E122: Accessories | F122: Webcam | G122: Hamza Shah | H122: 1 | I122: 10985.75 | J122: 0.1 | K122: 9887.18 | L122: 6329.93 | M122: 3557.25 | N122: Credit Card
... A125: ORD-2025-0124 | B125: 45745 | C125: Central | D125: Faisalabad | E125: Accessories | F125: Mouse | G125: Zara Iqbal | H125: 5 | I125: 4879.82 | J125: 0 | K125: 24399.1 | L125: 14008.06 | M125: 10391.04 | N125: Bank Transfer
A126: ORD-2025-0125 | B126: 08/06/2025 | C126: North | D126: Rawalpindi | E126: Electronics | F126: Smartphone | G126: Fatima Raza | H126: 7 | I126: 93308.19 | J126: 0.1 | K126: 587841.6 | L126: 464340.52 | M126: 123501.08 | N126: Credit Card
A127: ORD-2025-0126 | B127: 45988 | C127: South | D127: Karachi | E127: Electronics | F127: Laptop | G127: Usman Malik | H127: 4 | I127: 197015.31 | J127: 0.05 | K127: 748658.18 | L127: 564919.73 | M127: 183738.45 | N127: Credit Card
A128: ORD-2025-0127 | B128: 45979 | C128: North | D128: Islamabad | E128: Home Appliances | F128: Microwave | G128: Zara Iqbal | H128: 3 | I128: 33540.67 | J128: 0.15 | K128: 85528.71 | L128: 65831.04 | M128: 19697.67 | N128: Digital Wallet
A129: ORD-2025-0128 | B129: 45981 | C129: Central | D129: Multan | E129: Accessories | F129: Webcam | G129: Hamza Shah | H129: 6 | I129: 10857.76 | J129: 0 | K129: 65146.56 | L129: 39110.15 | M129: 26036.41 | N129: Bank Transfer
A130: ORD-2025-0129 | B130: 45804 | C130: Central | D130: Lahore | E130: Home Appliances | F130: Air Conditioner | G130: Sara Ahmed | H130: 5 | I130: 134173.64 | J130: 0 | K130: 670868.2 | L130: 491861.06 | M130: 179007.14 | N130: Cash
A131: ORD-2025-0130 | B131: 45822 | C131: Central | D131: Multan | E131: Accessories | F131: Mouse | G131: Zara Iqbal | H131: 1 | I131: 5158.18 | J131: 0.1 | K131: 4642.36 | L131: 2742.2 | M131: 1900.16 | N131: Credit Card
A132: ORD-2025-0131 | B132: 46020 | C132: North | D132: Rawalpindi | E132: Electronics | F132: Headphones | G132: Zara Iqbal | H132: 2 | I132: 14510.55 | J132: 0 | K132: 29021.1 | L132: 15952.94 | M132: 13068.16 | N132: Digital Wallet
A133: ORD-2025-0132 | B133: 45831 | C133: Central | D133: Multan | E133: Office Supplies | F133: Desk | G133: Ali Khan | H133: 6 | I133: 40541.06 | J133: 0.05 | K133: 231084.04 | L133: 155783.76 | M133: 75300.28 | N133: Bank Transfer
A134: ORD-2025-0133 | B134: 05-Nov-2025 | C134: North | D134: Rawalpindi | E134: Electronics | F134: Monitor | G134: Usman Malik | H134: 5 | I134: 49936.6 | J134: 0.15 | K134: 212230.55 | L134: 189345.34 | M134: 22885.21 | N134: Bank Transfer
A135: ORD-2025-0134 | B135: 45724 | C135: North | D135: Peshawar | E135: Office Supplies | F135: Desk | G135: Sara Ahmed | H135: 5 | I135: 40843.59 | J135: 0.15 | K135: 173585.26 | L135: 132125.43 | M135: 41459.83 | N135: Bank Transfer
A136: ORD-2025-0135 | B136: 45667 | C136: Central | D136: Faisalabad | E136: Home Appliances | F136: Microwave | G136: Fatima Raza | H136: 2 | I136: 33771.01 | J136: 0.05 | K136: 64164.92 | L136: 45251.74 | M136: 18913.18 | N136: Bank Transfer
...

Sheet Clean Data
A1: Order ID | B1: Order Date | C1: Region | D1: City | E1: Product Category | F1: Product | G1: Salesperson | H1: Units Sold | I1: Unit Price | J1: Discount | K1: Revenue | L1: Cost | M1: Profit | N1: Payment Method | O1: Profit Margin
A2: ORD-2025-0001 | B2: 45937 | C2: Central | D2: Lahore | E2: Electronics | F2: Headphones | G2: Sara Ahmed | H2: 4 | I2: 13857.85 | J2: 0.15 | K2: 47116.69 | L2: 32051.33 | M2: 15065.36 | N2: Digital Wallet | O2: =IFERROR(RawSalesTable_[[#This Row],[Profit]]/RawSalesTable_[[#This Row],[Revenue]],0) -> 0.31974572
A3: ORD-2025-0002 | B3: 45990 | C3: North | D3: Islamabad | E3: Electronics | F3: Smartphone | G3: Bilal Hussain | H3: 4 | I3: 92078.83 | J3: 0 | K3: 368315.32 | L3: 274526.11 | M3: 93789.21 | N3: Credit Card | O3: =IFERROR(RawSalesTable_[[#This Row],[Profit]]/RawSalesTable_[[#This Row],[Revenue]],0) -> 0.25464379
A4: ORD-2025-0003 | B4: 45768 | C4: South | D4: Quetta | E4: Home Appliances | F4: Air Conditioner | G4: Fatima Raza | H4: 3 | I4: 139279.81 | J4: 0.05 | K4: 396947.46 | L4: 299803.65 | M4: 97143.81 | N4: Cash | O4: =IFERROR(RawSalesTable_[[#This Row],[Profit]]/RawSalesTable_[[#This Row],[Revenue]],0) -> 0.24472712
A5: ORD-2025-0004 | B5: 45932 | C5: North | D5: Rawalpindi | E5: Electronics | F5: Headphones | G5: Sara Ahmed | H5: 6 | I5: 14740.64 | J5: 0 | K5: 88443.84 | L5: 50237.2 | M5: 38206.64 | N5: Digital Wallet | O5: =IFERROR(RawSalesTable_[[#This Row],[Profit]]/RawSalesTable_[[#This Row],[Revenue]],0) -> 0.43198758
A6: ORD-2025-0005 | B6: 45806 | C6: North | D6: Peshawar | E6: Home Appliances | F6: Vacuum Cleaner | G6: Sara Ahmed | H6: 4 | I6: 27883.75 | J6: 0 | K6: 111535 | L6: 73172.77 | M6: 38362.23 | N6: Credit Card | O6: =IFERROR(RawSalesTable_[[#This Row],[Profit]]/RawSalesTable_[[#This Row],[Revenue]],0) -> 0.34394791
A7: ORD-2025-0006 | B7: 45794 | C7: North | D7: Rawalpindi | E7: Home Appliances | F7: Water Dispenser | G7: Sara Ahmed | H7: 6 | I7: 23177.6 | J7: 0.05 | K7: 132112.32 | L7: 93346.29 | M7: 38766.03 | N7: Credit Card | O7: =IFERROR(RawSalesTable_[[#This Row],[Profit]]/RawSalesTable_[[#This Row],[Revenue]],0) -> 0.29343236
A8: ORD-2025-0007 | B8: 45770 | C8: Central | D8: Multan | E8: Office Supplies | F8: Office Chair | G8: Fatima Raza | H8: 8 | I8: 27950.32 | J8: 0.15 | K8: 190062.18 | L8: 154762.04 | M8: 35300.14 | N8: Cash | O8: =IFERROR(RawSalesTable_[[#This Row],[Profit]]/RawSalesTable_[[#This Row],[Revenue]],0) -> 0.18572943
A9: ORD-2025-0008 | B9: 45819 | C9: North | D9: Islamabad | E9: Home Appliances | F9: Water Dispenser | G9: Ayesha Noor | H9: 5 | I9: 22799.46 | J9: 0.1 | K9: 102597.57 | L9: 81476.31 | M9: 21121.26 | N9: Digital Wallet | O9: =IFERROR(RawSalesTable_[[#This Row],[Profit]]/RawSalesTable_[[#This Row],[Revenue]],0) -> 0.20586511
A10: ORD-2025-0009 | B10: 45792 | C10: South | D10: Quetta | E10: Accessories | F10: Usb Hub | G10: Bilal Hussain | H10: 5 | I10: 3957.83 | J10: 0.15 | K10: 16820.78 | L10: 10597.61 | M10: 6223.17 | N10: Digital Wallet | O10: =IFERROR(RawSalesTable_[[#This Row],[Profit]]/RawSalesTable_[[#This Row],[Revenue]],0) -> 0.36996917
A11: ORD-2025-0010 | B11: 45739 | C11: South | D11: Karachi | E11: Office Supplies | F11: Keyboard | G11: Bilal Hussain | H11: 2 | I11: 8847.86 | J11: 0 | K11: 17695.72 | L11: 9610.85 | M11: 8084.87 | N11: Cash | O11: =IFERROR(RawSalesTable_[[#This Row],[Profit]]/RawSalesTable_[[#This Row],[Revenue]],0) -> 0.45688279
A12: ORD-2025-0011 | B12: 45698 | C12: South | D12: Hyderabad | E12: Accessories | F12: Webcam | G12: Hamza Shah | H12: 1 | I12: 11831.72 | J12: 0 | K12: 11831.72 | L12: 6615.18 | M12: 5216.54 | N12: Bank Transfer | O12: =IFERROR(RawSalesTable_[[#This Row],[Profit]]/RawSalesTable_[[#This Row],[Revenue]],0) -> 0.44089448
A13: ORD-2025-0012 | B13: 45792 | C13: North | D13: Rawalpindi | E13: Accessories | F13: Usb Hub | G13: Usman Malik | H13: 8 | I13: 3866.18 | J13: 0.15 | K13: 26290.02 | L13: 17326 | M13: 8964.02 | N13: Cash | O13: =IFERROR(RawSalesTable_[[#This Row],[Profit]]/RawSalesTable_[[#This Row],[Revenue]],0) -> 0.34096665
... A1437: ORD-2025-1480 | B1437: 45681 | C1437: Central | D1437: Lahore | E1437: Electronics | F1437: Smartphone | G1437: Sara Ahmed | H1437: 3 | I1437: 95106.92 | J1437: 0.5 | K1437: 285320.76 | L1437: 212133.51 | M1437: 73187.25 | N1437: Digital Wallet | O1437: =IFERROR(RawSalesTable_[[#This Row],[Profit]]/RawSalesTable_[[#This Row],[Revenue]],0) -> 0.25650867

Sheet Analysis
E4: KPI | F4: Value
E6: Total Revenue | F6: =SUM(RawSalesTable_[Revenue]) -> 2.5552816e+08
E7: Total profit | F7: =SUM(RawSalesTable_[Profit]) -> 62309485
E8: Overall profit margin | F8: =F7/F6 -> 0.24384587
E9: Total Transactions | F9: =COUNTA(RawSalesTable_[Order ID]) -> 1436
E10: Total units sold | F10: =SUM(RawSalesTable_[Units Sold]) -> 6373

Sheet Pivot_Analysis
A4: Row Labels | B4: REVENUE | C4: PROFIT
A5: Central | B5: 79493158 | C5: 19434954
A6: North | B6: 93709201 | C6: 22791766
A7: South | B7: 82325796 | C7: 20082765
A8: Grand Total | B8: 2.5552816e+08 | C8: 62309485
A17: Row Labels | B17: Sum of Revenue
A18: Air Conditioner | B18: 46049744
A19: Laptop | B19: 58810127
A20: Microwave | B20: 13453895
A21: Monitor | B21: 17659357
A22: Smartphone | B22: 41872833
A23: Grand Total | B23: 1.7784596e+08
A31: Row Labels | B31: Sum of Revenue
A32: Ali Khan | B32: 31564555
A33: Ayesha Noor | B33: 24502798
A34: Bilal Hussain | B34: 39684213
A35: Fatima Raza | B35: 33899568
A36: Hamza Shah | B36: 31826740
A37: Sara Ahmed | B37: 32684982
A38: Usman Malik | B38: 28693708
A39: Zara Iqbal | B39: 32671591
A40: Grand Total | B40: 2.5552816e+08
A48: Row Labels | B48: Sum of Revenue
A49: Accessories | B49: 10243524
A50: Electronics | B50: 1.2373161e+08
A51: Home Appliances | B51: 82090558
A52: Office Supplies | B52: 39462463
A53: Grand Total | B53: 2.5552816e+08

Sheet DashBoard
A1: RETAIL SALES PERFORMANCE DASHBOARD
B4: TOTAL REVENUE | E4: TOTAL PROFIT | H4: PROFIT MARGIN | K4: TRANSACTIONS | N4: UNITS SOLD
B5: =Analysis!F6 -> 2.5552816e+08 | E5: =Analysis!F7 -> 62309485 | H5: =Analysis!F8 -> 0.24384587 | K5: =Analysis!F9 -> 1436 | N5: =Analysis!F10 -> 6373
